habana_lightning_plugins/__init__.py
habana_lightning_plugins/datamodule.py
habana_lightning_plugins/profiler.py
habana_lightning_plugins/utils.py
habana_lightning_plugins/dataloaders/__init__.py
habana_lightning_plugins/dataloaders/resnet_media_pipe.py
habana_lightning_plugins/fabric/__init__.py
habana_lightning_plugins-1.10.0.494.dist-info/LICENSE
habana_lightning_plugins-1.10.0.494.dist-info/METADATA
habana_lightning_plugins-1.10.0.494.dist-info/WHEEL
habana_lightning_plugins-1.10.0.494.dist-info/top_level.txt
habana_lightning_plugins-1.10.0.494.dist-info/RECORD
