Metadata-Version: 2.1
Name: habana-lightning-plugins
Version: 1.10.0.494
Summary: Habana's lightning-specific optimized plugins
Home-page: https://habana.ai/
Author: Habana Labs Ltd., an Intel Company
Author-email: support@habana.ai
License: See LICENSE file
Platform: UNKNOWN
Classifier: Development Status :: 5 - Production/Stable
Classifier: Intended Audience :: Developers
Classifier: Intended Audience :: Science/Research
Classifier: License :: Other/Proprietary License
Classifier: Operating System :: Unix
Classifier: Programming Language :: Python :: 3
Classifier: Programming Language :: Python :: 3.8
Classifier: Programming Language :: Python :: 3.10
Classifier: Programming Language :: Python :: 3 :: Only
Classifier: Topic :: Scientific/Engineering
Classifier: Topic :: Scientific/Engineering :: Mathematics
Classifier: Topic :: Scientific/Engineering :: Artificial Intelligence
Classifier: Topic :: Software Development
Classifier: Topic :: Software Development :: Libraries
Classifier: Topic :: Software Development :: Libraries :: Python Modules
License-File: LICENSE
Requires-Dist: pytorch-lightning
Requires-Dist: torch
Requires-Dist: torchvision
Requires-Dist: habana-torch-dataloader
Requires-Dist: habana-torch-plugin
